{
    "header_text": "Financial responsibilities: Feelings",
    "header_icon": "assets/subtitle.png",
    "elements": [
        {
            "type": "Text",
            "text": "Your partner was in the hospital recently and you have been helping to pay their medical bills. You wonder what this will mean for your finances moving forward.\n\nHere are some feelings that might happen in the moment:"
        },
        {
            "type": "TimedText",
            "text": null,
            "Duration": 15
        }
    ]
}